sparqldataframe/__init__.py
sparqldataframe-0.1.3.dist-info/LICENSE
sparqldataframe-0.1.3.dist-info/METADATA
sparqldataframe-0.1.3.dist-info/WHEEL
sparqldataframe-0.1.3.dist-info/top_level.txt
sparqldataframe-0.1.3.dist-info/RECORD
