Metadata-Version: 2.1
Name: sparqldataframe
Version: 0.1.3
Summary: Get a Pandas dataframe from SPARQL queries
Home-page: https://github.com/njanakiev/sparqldataframe
Author: Nikolai Janakiev
Author-email: nikolai.janakiev@gmail.com
License: MIT
Platform: any
Classifier: Environment :: Console
Classifier: Intended Audience :: Developers
Classifier: Intended Audience :: Science/Research
Classifier: Intended Audience :: System Administrators
Classifier: License :: OSI Approved :: MIT License
Classifier: Operating System :: POSIX
Classifier: Operating System :: MacOS
Classifier: Operating System :: Unix
Classifier: Operating System :: Microsoft :: Windows
Classifier: Programming Language :: Python
Classifier: Programming Language :: Python :: 2
Classifier: Programming Language :: Python :: 3
Classifier: Topic :: Scientific/Engineering :: Information Analysis
Classifier: Topic :: Software Development :: Libraries :: Python Modules
License-File: LICENSE
Requires-Dist: pandas
Requires-Dist: requests
Requires-Dist: simplejson
